codon_simulator.cp312-win_amd64.pyd
sequence_simulator.cp312-win_amd64.pyd
concentrations/Saccharomyces_cerevisiae.csv
concentrations/__init__.py
concentrations/basepairingeditor.py
concentrations/concentrations_generator.py
concentrations/default_basepairing.json
elongation/__init__.py
elongation/simulationbuilder.py
elongation/utils.py
elongation_simulator-1.1.0.data/scripts/basepairingeditor.py
elongation_simulator-1.1.0.data/scripts/simulationbuilder.py
elongation_simulator-1.1.0.dist-info/licenses/LICENSE
elongation_simulator-1.1.0.dist-info/METADATA
elongation_simulator-1.1.0.dist-info/WHEEL
elongation_simulator-1.1.0.dist-info/top_level.txt
elongation_simulator-1.1.0.dist-info/RECORD
