Metadata-Version: 2.4
Name: elongation_simulator
Version: 1.1.0
Summary: High-performance codon simulator and elongation simulator for eukaryotic organism
Home-page: https://github.com/fheday/elongation_simulator/
Author: Fabio Hedayioglu
Author-email: Fabio Hedayioglu <fheday@gmail.com>, Tobias von der Haar <T.von-der-Haar@kent.ac.uk>
Maintainer: Fabio Hedayioglu
Maintainer-email: Fabio Hedayioglu <fheday@gmail.com>
License: MIT License
Classifier: Development Status :: 5 - Production/Stable
Classifier: Intended Audience :: Science/Research
Classifier: License :: OSI Approved :: MIT License
Classifier: Programming Language :: C++
Classifier: Programming Language :: Python :: 3 :: Only
Classifier: Programming Language :: Python :: 3
Classifier: Programming Language :: Python :: 3.9
Classifier: Programming Language :: Python :: 3.10
Classifier: Programming Language :: Python :: 3.11
Classifier: Programming Language :: Python :: 3.12
Classifier: Programming Language :: Python :: 3.13
Requires-Python: >=3.9
License-File: LICENSE
Dynamic: author
Dynamic: home-page
Dynamic: license-file
Dynamic: maintainer
